          0 LOAD_FAST           0 (0)
          3 LOAD_GLOBAL         0 (0)
          6 BINARY_ADD
          7 STORE_FAST          1 (1)
         10 LOAD_CONST          1 (1)
         13 LOAD_CONST          2 (2)
         16 BUILD_LIST          2
         19 STORE_FAST          2 (2)
         22 LOAD_FAST           1 (1)
         25 LOAD_FAST           2 (2)
         28 LOAD_CONST          2 (2)
         31 STORE_SUBSCR
         32 LOAD_FAST           2 (2)
         35 LOAD_CONST          3 (3)
         38 BINARY_SUBSCR
         39 LOAD_FAST           2 (2)
         42 LOAD_CONST          2 (2)
         45 BINARY_SUBSCR
         46 BINARY_ADD
         47 STORE_FAST          1 (1)
         50 LOAD_FAST           1 (1)
         53 RETURN_VALUE
