          0 BUILD_MAP           2
          3 LOAD_CONST          1 (1)
          6 LOAD_CONST          2 (2)
          9 STORE_MAP
         10 LOAD_CONST          3 (3)
         13 LOAD_CONST          4 (4)
         16 STORE_MAP
         17 STORE_FAST          1 (1)
         20 LOAD_FAST           0 (0)
         23 STORE_FAST          2 (2)
         26 LOAD_FAST           2 (2)
         29 LOAD_CONST          1 (1)
         32 BINARY_SUBTRACT
         33 STORE_FAST          3 (3)
         36 LOAD_FAST           3 (3)
         39 LOAD_FAST           1 (1)
         42 LOAD_CONST          5 (5)
         45 STORE_SUBSCR
         46 LOAD_FAST           2 (2)
         49 RETURN_VALUE
